rknntools/__init__.py
rknntools/op_limit.py
rknntools-0.0.3.dist-info/LICENSE
rknntools-0.0.3.dist-info/METADATA
rknntools-0.0.3.dist-info/WHEEL
rknntools-0.0.3.dist-info/top_level.txt
rknntools-0.0.3.dist-info/RECORD
