Metadata-Version: 2.1
Name: rknntools
Version: 0.0.3
Summary: A utility toolkit for converting RKNN2 models, potentially used during the model transformation process.
Author-email: yuyun <15515722313@163.com>
License: MIT License
Project-URL: Homepage, https://github.com/yuyun2000
Classifier: Programming Language :: Python :: 3
Classifier: License :: OSI Approved :: MIT License
Classifier: Operating System :: OS Independent
Requires-Python: >=3.6
License-File: LICENSE
Requires-Dist: onnx >=1.13.1
